tradeapi.py
finamgrpc/__init__.py
finamgrpc/tradeapi/__init__.py
finamgrpc/tradeapi/v1/__init__.py
finamgrpc/tradeapi/v1/side_pb2.py
finamgrpc/tradeapi/v1/side_pb2_grpc.py
finamgrpc/tradeapi/v1/trade_pb2.py
finamgrpc/tradeapi/v1/trade_pb2_grpc.py
finamgrpc/tradeapi/v1/accounts/__init__.py
finamgrpc/tradeapi/v1/accounts/accounts_service_pb2.py
finamgrpc/tradeapi/v1/accounts/accounts_service_pb2_grpc.py
finamgrpc/tradeapi/v1/assets/__init__.py
finamgrpc/tradeapi/v1/assets/assets_service_pb2.py
finamgrpc/tradeapi/v1/assets/assets_service_pb2_grpc.py
finamgrpc/tradeapi/v1/auth/__init__.py
finamgrpc/tradeapi/v1/auth/auth_service_pb2.py
finamgrpc/tradeapi/v1/auth/auth_service_pb2_grpc.py
finamgrpc/tradeapi/v1/marketdata/__init__.py
finamgrpc/tradeapi/v1/marketdata/marketdata_service_pb2.py
finamgrpc/tradeapi/v1/marketdata/marketdata_service_pb2_grpc.py
finamgrpc/tradeapi/v1/orders/__init__.py
finamgrpc/tradeapi/v1/orders/orders_service_pb2.py
finamgrpc/tradeapi/v1/orders/orders_service_pb2_grpc.py
tradeapi-0.1.13.dist-info/licenses/LICENSE
tradeapi-0.1.13.dist-info/METADATA
tradeapi-0.1.13.dist-info/WHEEL
tradeapi-0.1.13.dist-info/top_level.txt
tradeapi-0.1.13.dist-info/RECORD
